README.md
license.txt
setup.py
renamefile/__init__.py
renamefile/renamefile.py
renamefile.egg-info/PKG-INFO
renamefile.egg-info/SOURCES.txt
renamefile.egg-info/dependency_links.txt
renamefile.egg-info/top_level.txt