Metadata-Version: 2.1
Name: renamefile
Version: 1.0.0
Summary: Escape from special characters in filenames
Author: @hackedubuntu
License: UNKNOWN
Platform: UNKNOWN
License-File: license.txt
